odoo8_addon_intrastat_product-8.0.1.5.0.99.dev10-py2.7-nspkg.pth
odoo8_addon_intrastat_product-8.0.1.5.0.99.dev10.dist-info/METADATA
odoo8_addon_intrastat_product-8.0.1.5.0.99.dev10.dist-info/RECORD
odoo8_addon_intrastat_product-8.0.1.5.0.99.dev10.dist-info/WHEEL
odoo8_addon_intrastat_product-8.0.1.5.0.99.dev10.dist-info/namespace_packages.txt
odoo8_addon_intrastat_product-8.0.1.5.0.99.dev10.dist-info/top_level.txt
odoo_addons/intrastat_product/README.rst
odoo_addons/intrastat_product/__init__.py
odoo_addons/intrastat_product/__openerp__.py
odoo_addons/intrastat_product/data/intrastat_transport_mode.xml
odoo_addons/intrastat_product/data/intrastat_unit.xml
odoo_addons/intrastat_product/demo/intrastat_demo.xml
odoo_addons/intrastat_product/i18n/intrastat_product.pot
odoo_addons/intrastat_product/models/__init__.py
odoo_addons/intrastat_product/models/account_invoice.py
odoo_addons/intrastat_product/models/hs_code.py
odoo_addons/intrastat_product/models/intrastat_product_declaration.py
odoo_addons/intrastat_product/models/intrastat_region.py
odoo_addons/intrastat_product/models/intrastat_transaction.py
odoo_addons/intrastat_product/models/intrastat_transport_mode.py
odoo_addons/intrastat_product/models/intrastat_unit.py
odoo_addons/intrastat_product/models/res_company.py
odoo_addons/intrastat_product/models/sale_order.py
odoo_addons/intrastat_product/models/stock_picking.py
odoo_addons/intrastat_product/models/stock_warehouse.py
odoo_addons/intrastat_product/security/intrastat_security.xml
odoo_addons/intrastat_product/security/ir.model.access.csv
odoo_addons/intrastat_product/views/account_invoice.xml
odoo_addons/intrastat_product/views/hs_code.xml
odoo_addons/intrastat_product/views/intrastat_product_declaration.xml
odoo_addons/intrastat_product/views/intrastat_region.xml
odoo_addons/intrastat_product/views/intrastat_transaction.xml
odoo_addons/intrastat_product/views/intrastat_transport_mode.xml
odoo_addons/intrastat_product/views/intrastat_unit.xml
odoo_addons/intrastat_product/views/res_company.xml
odoo_addons/intrastat_product/views/stock_picking.xml
odoo_addons/intrastat_product/views/stock_warehouse.xml
